[{
    "group": "Piano&E.Piano",
    "values": [{
      "name": "ConcertGrand"
    }, {
      "name": "BrightPiano"
    }, {
      "name": "MIDIGrand"
    }, {
      "name": "HonkyTonk"
    }, {
      "name": "OctavePiano"
    }, {
      "name": "GrandPiano"
    }, {
      "name": "WarmGrand"
    }, {
      "name": "BalladLayer"
    }, {
      "name": "CP80"
    }, {
      "name": "OctavePiano2"
    }, {
      "name": "SuitcaseEP"
    }, {
      "name": "JazzChorus"
    }, {
      "name": "ElectricPiano"
    }, {
      "name": "PhaseEP"
    }, {
      "name": "FunkEP"
    }, {
      "name": "TremoloEP"
    }, {
      "name": "StageEP"
    }, {
      "name": "VintageEP"
    }, {
      "name": "Clavi"
    }, {
      "name": "WahClavi"
    }, {
      "name": "SuperDX"
    }, {
      "name": "ModernEP"
    }, {
      "name": "VenusEP"
    }, {
      "name": "DXModern"
    }, {
      "name": "Harpsichord"
    }, {
      "name": "NewTines"
    }, {
      "name": "HyperTines"
    }, {
      "name": "PolarisEP"
    }, {
      "name": "GalaxyEP"
    }, {
      "name": "GrandHarpsi"
    }]
  },

  {
    "group": "Organ",
    "values": [{
      "name": "ScannerJazz"
    }, {
      "name": "ClassicJazz"
    }, {
      "name": "KeyClickJazz"
    }, {
      "name": "CurvedBars"
    }, {
      "name": "ElectricOrgan"
    }, {
      "name": "ChoraleJazz"
    }, {
      "name": "RotaryJazz"
    }, {
      "name": "ClickOrgan"
    }, {
      "name": "EvenBars"
    }, {
      "name": "RotorOrgan"
    }, {
      "name": "FullRocker"
    }, {
      "name": "BrightBars"
    }, {
      "name": "DrivenBars"
    }, {
      "name": "GospelOrgan"
    }, {
      "name": "PurpleOrgan"
    }, {
      "name": "RockChorale"
    }, {
      "name": "RockTremolo"
    }, {
      "name": "FullBars"
    }, {
      "name": "60sOrgan"
    }, {
      "name": "RotaryDrive"
    }, {
      "name": "ChapelOrgan"
    }, {
      "name": "HymnOrgan"
    }, {
      "name": "ChurchOrgan"
    }, {
      "name": "PipeOrgan"
    }, {
      "name": "HarmoniumDouble"
    }, {
      "name": "HomeTheater"
    }, {
      "name": "OpenTibias"
    }, {
      "name": "TibiaChorus"
    }, {
      "name": "ReedOrgan"
    }, {
      "name": "HarmoniumTriple"
    }, {
      "name": "EuroOrgan"
    }, {
      "name": "GameShow"
    }, {
      "name": "BalladOrgan"
    }, {
      "name": "BrightWheels"
    }, {
      "name": "DanceOrgan"
    }, {
      "name": "ClickOrganBass"
    }]
  },

  {
    "group": "Guitar&Bass",
    "values": [{
      "name": "DynoClassicGuitar"
    }, {
      "name": "SlideClassicGuitar"
    }, {
      "name": "SteelGuitar"
    }, {
      "name": "SlideSteelGuitar"
    }, {
      "name": "JazzGuitar"
    }, {
      "name": "SixtiesSolid"
    }, {
      "name": "CleanSolidDelay"
    }, {
      "name": "CreamyLeadGuitar"
    }, {
      "name": "HalfWahLead"
    }, {
      "name": "DistortionWah"
    }, {
      "name": "Guitar&Bass"
    }, {
      "name": "DynamicNylon"
    }, {
      "name": "DynamicSteel"
    }, {
      "name": "WarmSolid"
    }, {
      "name": "SlideSolid"
    }, {
      "name": "SolidJazz"
    }, {
      "name": "Cavaquinho"
    }, {
      "name": "ViolaCaipira"
    }, {
      "name": "Bandolim"
    }, {
      "name": "TremoloBandolim"
    }, {
      "name": "BandolimTouchTrem"
    }, {
      "name": "12StringGuitar"
    }, {
      "name": "Slide12String"
    }, {
      "name": "RockGuitar"
    }, {
      "name": "MutedGuitar"
    }, {
      "name": "SmoothJazz"
    }, {
      "name": "DynoDistortion"
    }, {
      "name": "DynoFeedback"
    }, {
      "name": "VintageLead"
    }, {
      "name": "PowerLead"
    }, {
      "name": "BluesGuitar"
    }, {
      "name": "CleanGuitar"
    }, {
      "name": "SlideClean"
    }, {
      "name": "ElectricGuitar"
    }, {
      "name": "VintageStrum"
    }, {
      "name": "PowerChord"
    }, {
      "name": "60sClean"
    }, {
      "name": "SmoothLead"
    }, {
      "name": "PedalSteel"
    }, {
      "name": "AlohaGuitar"
    }, {
      "name": "Mandolin"
    }, {
      "name": "VintageAmp"
    }, {
      "name": "CrunchGuitar"
    }, {
      "name": "CampfireGuitar"
    }, {
      "name": "SolidGuitar"
    }, {
      "name": "VintageOpen"
    }, {
      "name": "VintageMutedGt"
    }, {
      "name": "LeadGuitar"
    }, {
      "name": "ChorusGuitar"
    }, {
      "name": "VintageTrem"
    }, {
      "name": "OctaveGuitar"
    }, {
      "name": "DeepChorus"
    }, {
      "name": "BrightClean"
    }, {
      "name": "TremoloGuitar"
    }, {
      "name": "HeavyStack"
    }, {
      "name": "MutedGuitar"
    }, {
      "name": "Electric12String"
    }, {
      "name": "18StringGuitar"
    }, {
      "name": "FeedbackGuitar"
    }, {
      "name": "DistortionGuitar"
    }, {
      "name": "FunkGuitar"
    }, {
      "name": "WahGuitar"
    }, {
      "name": "VodooLead"
    }, {
      "name": "ClassicalGuitar"
    }, {
      "name": "FolkGuitar"
    }, {
      "name": "OverdriveGuitar"
    }, {
      "name": "SteelGuitar"
    }, {
      "name": "12StringGuitar"
    }, {
      "name": "HiStringGuitar"
    }, {
      "name": "NylonGuitar"
    }, {
      "name": "SolidGuitar"
    }, {
      "name": "DistortionGuitar"
    }, {
      "name": "Cavaquinho"
    }, {
      "name": "Bandolim"
    }, {
      "name": "ElectricBass"
    }, {
      "name": "DynoPickBass"
    }, {
      "name": "FretlessBass"
    }, {
      "name": "PickBass"
    }, {
      "name": "MutedPickBass"
    }, {
      "name": "AcousticBass"
    }, {
      "name": "MellowAcoBass"
    }, {
      "name": "RockBass"
    }, {
      "name": "DynoSlapBass"
    }, {
      "name": "SlapBass"
    }, {
      "name": "Bass&Cymbal"
    }, {
      "name": "HardBass"
    }, {
      "name": "ResoBass"
    }, {
      "name": "Guitar&Bass"
    }, {
      "name": "SuperFretless"
    }, {
      "name": "FusionBass"
    }, {
      "name": "SubBass"
    }, {
      "name": "MultiSawBass"
    }, {
      "name": "FilterEnvBass"
    }, {
      "name": "DX100Bass"
    }, {
      "name": "FatLoBass"
    }, {
      "name": "RampBass"
    }, {
      "name": "DarkCoreBass"
    }, {
      "name": "BleepBass"
    }, {
      "name": "AnalogBass"
    }, {
      "name": "DrySynthBass"
    }, {
      "name": "80sSynthBass"
    }, {
      "name": "HiQBass"
    }, {
      "name": "FunkBass"
    }, {
      "name": "ClickBass"
    }, {
      "name": "MellowFingerBass"
    }, {
      "name": "LFOSynBass"
    }, {
      "name": "AcousticBass"
    }, {
      "name": "ElectricBass"
    }, {
      "name": "PickBass"
    }]
  },

  {
    "group": "Accordion&Harmonica",
    "values": [{
      "name": "Accordion"
    }, {
      "name": "SmallAccordion"
    }, {
      "name": "TuttiAccordion"
    }, {
      "name": "Steirisch"
    }, {
      "name": "Musette"
    }, {
      "name": "Harmonica"
    }, {
      "name": "ModernHarp"
    }, {
      "name": "BluesHarp"
    }, {
      "name": "Bandoneon"
    }, {
      "name": "SoftAccordion"
    }, {
      "name": "BallroomAcc"
    }]
  },

  {
    "group": "Strings&Choir",
    "values": [{
      "name": "Strings"
    }, {
      "name": "StudioStrings"
    }, {
      "name": "Allegro"
    }, {
      "name": "SlowStrings"
    }, {
      "name": "OctaveStrings"
    }, {
      "name": "Marcato"
    }, {
      "name": "ConcertoStrings"
    }, {
      "name": "OrchStrings"
    }, {
      "name": "TremoloStrings"
    }, {
      "name": "Pizzicato"
    }, {
      "name": "Violin"
    }, {
      "name": "Viola"
    }, {
      "name": "Cello"
    }, {
      "name": "Contrabass"
    }, {
      "name": "Harp"
    }, {
      "name": "Strings&Flutes"
    }, {
      "name": "OctStrings&Flutes"
    }, {
      "name": "OrchestralPad"
    }, {
      "name": "Horns&Strings"
    }, {
      "name": "Tutti"
    }, {
      "name": "SoloViolin"
    }, {
      "name": "FastStrings"
    }, {
      "name": "BowStrings"
    }, {
      "name": "AnalogStrings"
    }, {
      "name": "SynthStrings"
    }, {
      "name": "HahChoir"
    }, {
      "name": "Choir"
    }, {
      "name": "GothicVox"
    }, {
      "name": "AirChoir"
    }, {
      "name": "VoxHumana"
    }, {
      "name": "Fiddle"
    }, {
      "name": "Banjo"
    }, {
      "name": "Hackbrett"
    }, {
      "name": "Sitar"
    }, {
      "name": "BrightSitar"
    }, {
      "name": "Koto"
    }, {
      "name": "Shamisen"
    }, {
      "name": "Oud"
    }, {
      "name": "Kanoun"
    }, {
      "name": "Watariyat"
    }, {
      "name": "ErHu"
    }, {
      "name": "PiPa"
    }, {
      "name": "Orchestra"
    }, {
      "name": "Symphonic"
    }, {
      "name": "Strings&Choir"
    }, {
      "name": "GospelVoices"
    }, {
      "name": "StringQuartet"
    }, {
      "name": "ChamberStrings"
    }, {
      "name": "OrchestraHit"
    }]
  },

  {
    "group": "Brass",
    "values": [{
      "name": "PopBrass"
    }, {
      "name": "OctaveBrass"
    }, {
      "name": "BrightBrass"
    }, {
      "name": "MellowBrass"
    }, {
      "name": "SoftBrass"
    }, {
      "name": "FullHorns"
    }, {
      "name": "MellowHorns"
    }, {
      "name": "PopBrass"
    }, {
      "name": "BigBrass"
    }, {
      "name": "BrassSection"
    }, {
      "name": "HyperBrass"
    }, {
      "name": "80sBrass"
    }, {
      "name": "HighBrass"
    }, {
      "name": "OberBrass"
    }, {
      "name": "AnalogBrass"
    }, {
      "name": "SoftAnalog"
    }, {
      "name": "FunkyAnalog"
    }, {
      "name": "TechnoBrass"
    }, {
      "name": "SynthBrass"
    }, {
      "name": "BrassHit"
    }, {
      "name": "FrenchHorns"
    }, {
      "name": "Sforzando"
    }, {
      "name": "SmoothTrombone"
    }, {
      "name": "TrumpetEns"
    }, {
      "name": "TromboneSection"
    }, {
      "name": "BrassCombo"
    }, {
      "name": "BallroomBrass"
    }, {
      "name": "BigBandBrass"
    }, {
      "name": "SmallBrass"
    }, {
      "name": "Tuba"
    }, {
      "name": "Trumpet"
    }, {
      "name": "MutedTrumpet"
    }, {
      "name": "JazzTrumpet"
    }, {
      "name": "FlugelHorn"
    }, {
      "name": "Trombone"
    }, {
      "name": "SoftTrombone"
    }, {
      "name": "SoloTrombone"
    }, {
      "name": "BaritoneHorn"
    }, {
      "name": "BaritoneHit"
    }, {
      "name": "AlpBass"
    }, {
      "name": "SoloTrumpet"
    }, {
      "name": "MutedTrumpet"
    }, {
      "name": "Trombone"
    }, {
      "name": "FlugelHorn"
    }, {
      "name": "MellowTrombone"
    }]
  },

  {
    "group": "Woodwind",
    "values": [{
      "name": "TenorSax"
    }, {
      "name": "AltoSax"
    }, {
      "name": "SopranoSax"
    }, {
      "name": "JazzTenor"
    }, {
      "name": "PopTenor"
    }, {
      "name": "GrowlSax"
    }, {
      "name": "SaxSection"
    }, {
      "name": "SaxSectionHard"
    }, {
      "name": "SaxSectionSoft"
    }, {
      "name": "BaritoneSax"
    }, {
      "name": "BalladTenor"
    }, {
      "name": "AltoSax"
    }, {
      "name": "SoftSoprano"
    }, {
      "name": "BreathyTenor"
    }, {
      "name": "HardTenor"
    }, {
      "name": "ClassicalFlute"
    }, {
      "name": "ClassicalClarinet"
    }, {
      "name": "ClassicalOboe"
    }, {
      "name": "EnglishHorn"
    }, {
      "name": "Bassoon"
    }, {
      "name": "JazzFlute"
    }, {
      "name": "BreathyFlute"
    }, {
      "name": "OrchestralOboe"
    }, {
      "name": "JazzClarinet"
    }, {
      "name": "Piccolo"
    }, {
      "name": "BalladPanFlute"
    }, {
      "name": "ChiffPanFlute"
    }, {
      "name": "Woodwind"
    }, {
      "name": "Whistle"
    }, {
      "name": "Recorder"
    }, {
      "name": "WoodwindsEns"
    }, {
      "name": "Ocarina"
    }, {
      "name": "Bagpipe"
    }, {
      "name": "EthnicFlute"
    }, {
      "name": "Shakuhachi"
    }, {
      "name": "Nay"
    }, {
      "name": "DiZi"
    }, {
      "name": "Sheng"
    }]
  },

  {
    "group": "Synth",
    "values": [{
      "name": "Gemini"
    }, {
      "name": "HandsUp!"
    }, {
      "name": "PunchyChordz"
    }, {
      "name": "DeepSubMW"
    }, {
      "name": "RSDualSquare"
    }, {
      "name": "RSSawLead1"
    }, {
      "name": "RSSawLead2"
    }, {
      "name": "RSDualSaw"
    }, {
      "name": "RSTechSaw"
    }, {
      "name": "RSRampLead"
    }, {
      "name": "RSDistortionLead"
    }, {
      "name": "RSQuackLead"
    }, {
      "name": "BriteDecay"
    }, {
      "name": "RSSync1"
    }, {
      "name": "RSSync2"
    }, {
      "name": "RSShortResonance"
    }, {
      "name": "DancyHook"
    }, {
      "name": "ClubLead"
    }, {
      "name": "ResoLead"
    }, {
      "name": "DanceLead"
    }, {
      "name": "VCFDance"
    }, {
      "name": "DanceHook"
    }, {
      "name": "TranceSeq"
    }, {
      "name": "Oxygen"
    }, {
      "name": "Matrix"
    }, {
      "name": "WireLead"
    }, {
      "name": "HipLead"
    }, {
      "name": "HopLead"
    }, {
      "name": "FireWire"
    }, {
      "name": "Analogon"
    }, {
      "name": "Blaster"
    }, {
      "name": "Skyline"
    }, {
      "name": "SquareLead"
    }, {
      "name": "SawLead"
    }, {
      "name": "TinyLead"
    }, {
      "name": "FunkyLead"
    }, {
      "name": "Paraglide"
    }, {
      "name": "Portatone"
    }, {
      "name": "BigLead"
    }, {
      "name": "Warp"
    }, {
      "name": "Fargo"
    }, {
      "name": "Adrenaline"
    }, {
      "name": "Stardust"
    }, {
      "name": "AeroLead"
    }, {
      "name": "MiniLead"
    }, {
      "name": "Impact"
    }, {
      "name": "SunBell"
    }, {
      "name": "UnderHeim"
    }, {
      "name": "HiBias"
    }, {
      "name": "VinylLead"
    }, {
      "name": "RSWarmPad"
    }, {
      "name": "RSNoisePad"
    }, {
      "name": "RSTeknoMan"
    }, {
      "name": "RSAnalogPad"
    }, {
      "name": "RSSynthPad"
    }, {
      "name": "VPSoft"
    }, {
      "name": "DarkFatSaw"
    }, {
      "name": "LightPad"
    }, {
      "name": "VanillaPad"
    }, {
      "name": "VanillaWarmth"
    }, {
      "name": "ButterStrings"
    }, {
      "name": "SweetHeaven"
    }, {
      "name": "DreamHeaven"
    }, {
      "name": "Insomnia"
    }, {
      "name": "NeoWarmPad"
    }, {
      "name": "CyberPad"
    }, {
      "name": "Synth"
    }, {
      "name": "Wave2001"
    }, {
      "name": "Atmosphere"
    }, {
      "name": "XenonPad"
    }, {
      "name": "Equinox"
    }, {
      "name": "Fantasia"
    }, {
      "name": "DXPad"
    }, {
      "name": "Symbiont"
    }, {
      "name": "Stargate"
    }, {
      "name": "Area51"
    }, {
      "name": "DarkMoon"
    }, {
      "name": "Ionosphere"
    }, {
      "name": "GoldenAge"
    }, {
      "name": "Solaris"
    }, {
      "name": "Millennium"
    }, {
      "name": "Dunes"
    }, {
      "name": "LFOSync1"
    }, {
      "name": "LFOSync2"
    }, {
      "name": "LFOSync3"
    }, {
      "name": "LFOSync4"
    }, {
      "name": "LFOSync5"
    }, {
      "name": "LFOPad"
    }, {
      "name": "Noise"
    }]
  },

  {
    "group": "Perc.&Drums",
    "values": [{
      "name": "Vibraphone"
    }, {
      "name": "JazzVibes"
    }, {
      "name": "Glockenspiel"
    }, {
      "name": "Xylophone"
    }, {
      "name": "Marimba"
    }, {
      "name": "Celesta"
    }, {
      "name": "TubularBells"
    }, {
      "name": "SteelDrums"
    }, {
      "name": "MusicBox"
    }, {
      "name": "Timpani"
    }, {
      "name": "FastRotaryVibes"
    }, {
      "name": "StraightVibes"
    }, {
      "name": "Kalimba"
    }, {
      "name": "Dulcimer"
    }, {
      "name": "PowerKit1"
    }, {
      "name": "PowerKit2"
    }, {
      "name": "StandardKit1"
    }, {
      "name": "StandardKit2"
    }, {
      "name": "HitKit"
    }, {
      "name": "JazzKit"
    }, {
      "name": "BrushKit"
    }, {
      "name": "RoomKit"
    }, {
      "name": "RockKit"
    }, {
      "name": "ElectroKit"
    }, {
      "name": "HouseKit"
    }, {
      "name": "AnalogT8Kit"
    }, {
      "name": "AnalogT9Kit"
    }, {
      "name": "BreakKit"
    }, {
      "name": "HipHopKit"
    }, {
      "name": "AnalogKit"
    }, {
      "name": "DanceKit"
    }, {
      "name": "SymphonyKit"
    }, {
      "name": "BrasilKit1"
    }, {
      "name": "BrasilKit2"
    }, {
      "name": "Berimbau&Surdo"
    }, {
      "name": "CubanKit"
    }, {
      "name": "PopLatinKit"
    }, {
      "name": "ArabicKit1"
    }, {
      "name": "ArabicKit2"
    }, {
      "name": "ArabicMixtureKit"
    }, {
      "name": "IndianKit"
    }, {
      "name": "ChineseKit"
    }, {
      "name": "ChineseMixtureKit"
    }, {
      "name": "BassDrumKit"
    }, {
      "name": "ReverseBsDrumKit"
    }, {
      "name": "SFXKit1"
    }, {
      "name": "SFXKit2"
    }, {
      "name": "AnimalKit"
    }]
  }
]